sms_sender/__init__.py
sms_sender/utils.py
onfon_sms_sender-0.1.4.dist-info/LICENSE
onfon_sms_sender-0.1.4.dist-info/METADATA
onfon_sms_sender-0.1.4.dist-info/WHEEL
onfon_sms_sender-0.1.4.dist-info/top_level.txt
onfon_sms_sender-0.1.4.dist-info/RECORD
