Metadata-Version: 2.1
Name: onfon-sms-sender
Version: 0.1.4
Summary: A package to send SMS using Onfon Media API
Home-page: https://github.com/antonnifo/Onfon-SMS-Sender
Author: Antonnifo
Author-email: antonnifo@live.com
License: MIT
Classifier: Development Status :: 3 - Alpha
Classifier: Intended Audience :: Developers
Classifier: Topic :: Software Development :: Libraries :: Python Modules
Classifier: License :: OSI Approved :: MIT License
Classifier: Programming Language :: Python :: 3.6
Classifier: Programming Language :: Python :: 3.7
Classifier: Programming Language :: Python :: 3.8
Classifier: Programming Language :: Python :: 3.9
License-File: LICENSE
Requires-Dist: requests
Requires-Dist: python-dotenv
